agentspro/Text2Agent.py
agentspro/__init__.py
agentspro/agentify/FlowGraph.py
agentspro/agentify/FlowInterpreter.py
agentspro/agentify/NodeRegistry.py
agentspro/agentify/Utils.py
agentspro/agentify/__init__.py
agentspro/agentify/prompt.md
agentspro/agentify/api/GraphAPI.py
agentspro/agentify/types/GraphTypes.py
agentspro/agentify/types/__init__.py
agentspro/dify/DifyGraph.py
agentspro/dify/DifyTypes.py
agentspro/dify/__init__.py
agentspro-0.1.1.dist-info/METADATA
agentspro-0.1.1.dist-info/WHEEL
agentspro-0.1.1.dist-info/entry_points.txt
agentspro-0.1.1.dist-info/RECORD
