Metadata-Version: 2.4
Name: agentspro
Version: 0.1.1
Summary: The AI Agent Decorator SDK for Agentspro platform integration
Author-email: Hehua Fan <forhheart5532@gmail.com>
Requires-Python: >=3.11
Requires-Dist: pydantic>=2.11.7
Requires-Dist: pyyaml>=6.0
Requires-Dist: requests>=2.32.4
